nestedlistops/README.MD
nestedlistops/__init__.py
nestedlistops/requirements.txt
nestedlistops/thirdparty.json
nestedlistops-0.10.dist-info/LICENSE.rst
nestedlistops-0.10.dist-info/METADATA
nestedlistops-0.10.dist-info/WHEEL
nestedlistops-0.10.dist-info/top_level.txt
nestedlistops-0.10.dist-info/RECORD
