Metadata-Version: 2.1
Name: nestedlistops
Version: 0.10
Summary: easier access to nested lists
Home-page: https://github.com/hansalemaos/nestedlistops
Author: Johannes Fischer
Author-email: aulasparticularesdealemaosp@gmail.com
License: MIT
Keywords: nested,list
Classifier: Development Status :: 4 - Beta
Classifier: Programming Language :: Python :: 3 :: Only
Classifier: Programming Language :: Python :: 3.10
Classifier: Topic :: Software Development :: Libraries :: Python Modules
Classifier: Topic :: Utilities
License-File: LICENSE.rst
